macarna/__init__.py
macarna/__main__.py
macarna/mac_db.dump
macarna/mac_lookup.py
macarna-0.0.5.dist-info/AUTHORS
macarna-0.0.5.dist-info/LICENSE
macarna-0.0.5.dist-info/METADATA
macarna-0.0.5.dist-info/WHEEL
macarna-0.0.5.dist-info/top_level.txt
macarna-0.0.5.dist-info/RECORD
