Metadata-Version: 2.1
Name: macarna
Version: 0.0.5
Summary: Fast offline vendor lookup by MAC address
Home-page: UNKNOWN
Author: Tarik K
Author-email: sjtarik@gmail.com
License: UNKNOWN
Keywords: mac-address vendor lookup
Platform: UNKNOWN
Classifier: Development Status :: 3 - Alpha
Classifier: Programming Language :: Python
Requires-Python: <4, >=3.7
License-File: LICENSE
License-File: AUTHORS
Requires-Dist: msgpack
